{
  "build_id": "sbx-20260225-132308",
  "skill": "plan",
  "version": "22.0.0-hardened",
  "started_at": "2026-02-25T13:23:08.586456",
  "status": "completed",
  "total_cycles": 1,
  "cycles": [
    {
      "cycle_number": 1,
      "started_at": "2026-02-25T13:23:08.586459",
      "steps": {
        "init": {
          "required": true,
          "executed": true,
          "executed_at": "2026-02-25T13:23:08.586483",
          "result": "success"
        },
        "validate_input": {
          "required": true,
          "executed": true,
          "executed_at": "2026-02-25T13:23:28.637383",
          "spec_path": "docs/MEDICUM_FUNCTIONAL_SPEC.md",
          "spec_exists": true,
          "requirement_count": 65,
          "result": "success"
        },
        "parse_spec": {
          "required": true,
          "executed": true,
          "executed_at": "2026-02-25T13:23:47.651027",
          "output_path": ".sbx/medicum-parsed-spec.json",
          "parsed_requirements": 0,
          "result": "incomplete",
          "physical_verification": {
            "file_exists": true,
            "valid_json": true,
            "requirement_count": 0,
            "issues": [
              "Parsed 0 reqs but spec has 65"
            ]
          }
        },
        "create_build_plan": {
          "required": true,
          "executed": true,
          "executed_at": "2026-02-25T13:27:06.579747",
          "output_path": "docs/MEDICUM_BUILD_PLAN.md",
          "physical_verification": {
            "file_exists": true,
            "has_structure": true,
            "task_count": 65,
            "has_coverage_matrix": true,
            "issues": []
          },
          "file_hash": "3d330473dac8f3cfeea8074ba1c62dc79a673af9c10d0ea6bb5322bdf29d351f",
          "result": "success"
        },
        "create_progress": {
          "required": true,
          "executed": true,
          "executed_at": "2026-02-25T13:27:59.883068",
          "physical_verification": {
            "file_exists": true,
            "all_pending": true,
            "checkbox_count": 168,
            "issues": []
          },
          "result": "success"
        },
        "create_test_plan": {
          "required": true,
          "executed": true,
          "executed_at": "2026-02-25T13:30:48.328173",
          "output_path": "docs/MEDICUM_TEST_PLAN.md",
          "physical_verification": {
            "file_exists": true,
            "unit_count": 65,
            "integration_count": 8,
            "e2e_count": 11,
            "issues": []
          },
          "file_hash": "4e3f529de9606eae0c0202ae0e76223d995ef4a90da5d707276ab7abc5b9fc22",
          "result": "success"
        },
        "verify_documents": {
          "required": true,
          "executed": true,
          "executed_at": "2026-02-25T13:31:06.044718",
          "enforcer_ran_directly": true,
          "requirement_coverage": {
            "total_requirements": 65,
            "requirements_with_tasks": 65,
            "requirements_with_tests": 65,
            "coverage_percent": 100.0,
            "uncovered": []
          },
          "document_hashes_step": "verify_documents",
          "result": "passed",
          "coverage_matrix": {
            "has_section": true,
            "has_all_columns": false,
            "row_count": 130
          }
        },
        "gap_analyzer": {
          "required": true,
          "executed": true,
          "executed_at": "2026-02-25T13:31:22.416070",
          "gaps_found": 0,
          "critical_gaps": 0,
          "result": "passed",
          "enforcer_ran_directly": true
        },
        "verify_gaps": {
          "required": true,
          "executed": true,
          "executed_at": "2026-02-25T13:31:38.148070",
          "enforcer_ran_directly": true,
          "critical_resolved": 0,
          "critical_unresolved": [],
          "result": "passed",
          "total_gaps": 0,
          "critical_gaps": 0,
          "critical_deferred": []
        },
        "design_review": {
          "required": false,
          "executed": true,
          "executed_at": "2026-02-25T13:34:50.814177",
          "agent_ran": true,
          "skipped": false,
          "issues_found": 0,
          "semantic_checks": {
            "us_to_req_coherence": false,
            "br_to_tech_coverage": false,
            "acceptance_criteria": false
          },
          "result": "passed"
        },
        "analyze_phase": {
          "required": true,
          "executed": true,
          "executed_at": "2026-02-25T13:35:08.097204",
          "compliance_score": 100.0,
          "result": "passed",
          "enforcer_ran_directly": true
        },
        "finalize": {
          "required": true,
          "executed": true,
          "executed_at": "2026-02-25T13:35:25.135275",
          "toctou_check": {
            "documents_unchanged": true,
            "modified_files": [],
            "deleted_files": []
          },
          "result": "success"
        }
      },
      "completed": true,
      "completed_at": "2026-02-25T13:35:25.135280"
    }
  ],
  "project_name": "medicum",
  "completed_at": "2026-02-25T13:35:25.135282",
  "_signature": "8ae7b3173ec444a58864d50f8947d9bc07e616755c91f0ac3cfe49ec21dc6d1a"
}